ToontownUtils/Body.py
ToontownUtils/CogActor.py
ToontownUtils/CogGlobals.py
ToontownUtils/Department.py
ToontownUtils/TemplateCog.py
ToontownUtils/TemplateManager.py
ToontownUtils/__init__.py
toontownutils-1.0.0.dist-info/METADATA
toontownutils-1.0.0.dist-info/WHEEL
toontownutils-1.0.0.dist-info/licenses/LICENSE
toontownutils-1.0.0.dist-info/RECORD
