Metadata-Version: 2.1
Name: ToontownUtils
Version: 1.0.0
Summary: Toontown-specific utilities for Panda3D
Project-URL: Homepage, https://github.com/demiurgeQuantified/ToontownUtils
Project-URL: Bug Tracker, https://github.com/demiurgeQuantified/ToontownUtils/issues
Author-email: albion <demiurgequantified@gmail.com>
License-File: LICENSE
Classifier: License :: OSI Approved :: MIT License
Classifier: Operating System :: OS Independent
Classifier: Programming Language :: Python :: 3
Requires-Python: >=3.10
Requires-Dist: panda3d
